{
  "id": "ct-neck",
  "name": "КТ м'яких тканин шиї",
  "modality": "CT",
  "bodyPart": "neck",
  "language": "uk",
  "version": "1.0.0",
  "sections": [
    {
      "id": "patient_info",
      "title": "Дані пацієнта",
      "type": "group",
      "subsections": [
        { "id": "patient_name", "title": "ПІБ пацієнта", "defaultText": "" },
        { "id": "patient_dob", "title": "Дата народження пацієнта", "defaultText": "", "placeholder": "ДД/ММ/РРРР" },
        { "id": "patient_id", "title": "ID пацієнта", "defaultText": "" },
        { "id": "exam_date", "title": "Дата обстеження", "defaultText": "", "placeholder": "ДД/ММ/РРРР" }
      ]
    },
    {
      "id": "clinical_info",
      "title": "Клінічна інформація",
      "type": "free_text",
      "defaultText": "Не надано.",
      "placeholder": "Показання: утворення шиї / лімфаденопатія / стадіювання пухлини / абсцес / дисфагія / інше"
    },
    {
      "id": "technique",
      "title": "Методика дослідження",
      "type": "free_text",
      "defaultText": "КТ м'яких тканин шиї від основи черепа до дуги аорти з внутрішньовенним контрастним підсиленням. Товщина зрізу 1 мм."
    },
    {
      "id": "quality",
      "title": "Якість дослідження",
      "type": "free_text",
      "defaultText": "Якість дослідження задовільна. Контрастне підсилення адекватне."
    },
    {
      "id": "comparison",
      "title": "Порівняння",
      "type": "free_text",
      "defaultText": "Попередні дослідження для порівняння відсутні.",
      "placeholder": "Порівняння з попередніми дослідженнями (дата, метод)"
    },
    {
      "id": "findings",
      "title": "Опис",
      "type": "group",
      "subsections": [
        {
          "id": "nasopharynx",
          "title": "Носоглотка",
          "defaultText": "Носоглотка без об'ємних утворень. Аденоїдна тканина не гіпертрофована. Глоткові отвори слухових труб вільні.",
          "normalText": "Носоглотка без об'ємних утворень."
        },
        {
          "id": "oropharynx",
          "title": "Ротоглотка",
          "defaultText": "Ротоглотка без об'ємних утворень. Піднебінні мигдалики не збільшені. Язик, дно ротової порожнини без патологічних змін.",
          "normalText": "Ротоглотка без об'ємних утворень."
        },
        {
          "id": "larynx_hypopharynx",
          "title": "Гортань та гортаноглотка",
          "defaultText": "Гортань симетрична. Голосові складки рухливі, не потовщені. Грушоподібні синуси вільні. Надгортанник не змінений. Підзв'язковий простір не звужений.",
          "normalText": "Гортань симетрична. Голосові складки не потовщені. Грушоподібні синуси вільні."
        },
        {
          "id": "thyroid",
          "title": "Щитоподібна залоза",
          "defaultText": "Щитоподібна залоза звичайних розмірів, однорідної структури, без вогнищевих змін.",
          "normalText": "Щитоподібна залоза звичайних розмірів, без вогнищевих змін."
        },
        {
          "id": "salivary_glands",
          "title": "Слинні залози",
          "defaultText": "Привушні та піднижньощелепні слинні залози симетричні, без вогнищевих змін.",
          "normalText": "Слинні залози симетричні, без вогнищевих змін."
        },
        {
          "id": "lymph_nodes_neck",
          "title": "Лімфатичні вузли шиї",
          "defaultText": "Лімфатичні вузли шиї не збільшені (рівні I–VI за класифікацією).",
          "normalText": "Лімфатичні вузли шиї не збільшені."
        },
        {
          "id": "vessels_neck",
          "title": "Судини шиї",
          "defaultText": "Сонні та хребтові артерії прохідні, без значних стенозів. Яремні вени не розширені.",
          "normalText": "Сонні та хребтові артерії прохідні. Яремні вени не розширені."
        },
        {
          "id": "spaces_neck",
          "title": "Фасціальні простори",
          "defaultText": "Фасціальні простори шиї без патологічних скупчень рідини чи газу.",
          "normalText": "Фасціальні простори шиї без патологічних змін."
        },
        {
          "id": "bones_neck",
          "title": "Кісткові структури",
          "defaultText": "Кісткові структури шийного відділу хребта, нижньої щелепи та під'язикової кістки без деструктивних змін.",
          "normalText": "Кісткові структури без деструктивних змін."
        }
      ]
    },
    {
      "id": "impression",
      "title": "Висновок",
      "type": "free_text",
      "defaultText": "КТ-ознаки патологічних змін м'яких тканин шиї не виявлено."
    },
    {
      "id": "recommendations",
      "title": "Рекомендації",
      "type": "free_text",
      "defaultText": "",
      "placeholder": "За потреби вкажіть рекомендації"
    }
  ],
  "checklist": [
    { "id": "cl_indication", "category": "Клінічні дані", "item": "Показання до дослідження", "keywords": ["показання", "утворення", "лімфаденопат", "стадіюван", "абсцес"] },
    { "id": "cl_mass", "category": "Утворення", "item": "Об'ємне утворення (локалізація, розміри)", "keywords": ["утворення", "маса", "пухлин", "новоутвор"] },
    { "id": "cl_lymph_nodes_level", "category": "Лімфовузли", "item": "Лімфаденопатія (рівень I–VI)", "keywords": ["лімфовузл", "лімфаденопат", "рівень", "збільшен", "конгломерат", "некроз"] },
    { "id": "cl_thyroid_nodule", "category": "Щитоподібна залоза", "item": "Вузлові утворення щитоподібної залози", "keywords": ["щитоподібн", "вузол", "утворення", "кальцифікац"] },
    { "id": "cl_larynx", "category": "Гортань", "item": "Патологія гортані / голосових складок", "keywords": ["гортан", "голосов", "складк", "надгортанник", "потовщен"] },
    { "id": "cl_abscess", "category": "Інфекція", "item": "Абсцес / флегмона", "keywords": ["абсцес", "флегмон", "скупчення рідин", "газ", "запальн"] },
    { "id": "cl_salivary", "category": "Слинні залози", "item": "Патологія слинних залоз", "keywords": ["слинн", "привушн", "піднижньощелепн", "камін", "протока"] },
    { "id": "cl_vessels", "category": "Судини", "item": "Стенози / тромбози судин шиї", "keywords": ["стеноз", "тромбоз", "сонн", "яремн", "хребтов артері"] },
    { "id": "cl_invasion", "category": "Інвазія", "item": "Інвазія в судини / кістки / простори", "keywords": ["інвазі", "проростан", "деструкці", "інфільтраці"] },
    { "id": "cl_airway", "category": "Дихальні шляхи", "item": "Прохідність дихальних шляхів", "keywords": ["дихальн", "прохідн", "звужен", "обструкці", "трахе"] }
  ]
}
